{
  "description": "JSON Schema definition of the quirks of different CHIP-8 systems.",
  "definitions": {
    "quirk": {
      "type": "object",
      "properties": {
        "id": {
          "type": "string",
          "description": "An ID for this quirk, by which to reference it in programs.json or platforms.json."
        },
        "name": {
          "type": "string",
          "description": "The name of this quirk."
        },
        "description": {
          "type": "string",
          "description": "A description of the quirk and why it exists."
        },
        "default": {
          "type": "boolean",
          "description": "Whether or not this quirk should be enabled by default."
        },
        "ifTrue": {
          "type": "string",
          "description": "A description of CHIP-8 behavior when this quirk is enabled."
        },
        "ifFalse": {
          "type": "string",
          "description": "A description of CHIP-8 behavior when this quirk is not enabled."
        }
      },
      "required": ["id", "name", "default", "ifTrue", "ifFalse"],
      "additionalProperties": false
    }
  },
  "type": "array",
  "items": {
    "$ref": "#/definitions/quirk"
  }
}
